{"技能1": {"名称": "雷电拳", "简介": "用充满电流的拳头攻击对手。有时会让对手陷入麻痹状态。", "属性": "电", "类型": "物理", "威力": "75", "命中": "100", "PP": "15"}, "技能2": {"名称": "电击", "简介": "发出电流刺激对手进行攻击。有时会让对手陷入麻痹状态。", "属性": "电", "类型": "特殊", "威力": "40", "命中": "100", "PP": "30"}, "技能3": {"名称": "摇尾巴", "简介": "可爱地左右摇晃尾巴，诱使对手疏忽大意。会降低对手的防御。", "属性": "一般", "类型": "变化", "威力": "—", "命中": "100", "PP": "30"}, "技能4": {"名称": "和睦相处", "简介": "和对手和睦相处，使其失去战斗的气力，从而降低对手的攻击。", "属性": "一般", "类型": "变化", "威力": "—", "命中": "—", "PP": "20"}, "技能5": {"名称": "天使之吻", "简介": "像天使般可爱地亲吻对手，从而使对手混乱。", "属性": "妖精", "类型": "变化", "威力": "—", "命中": "75", "PP": "10"}, "技能6": {"名称": "蹭蹭脸颊", "简介": "将带电的脸颊蹭蹭对手进行攻击。让对手陷入麻痹状态。", "属性": "电", "类型": "物理", "威力": "20", "命中": "100", "PP": "20"}, "技能7": {"名称": "诡计", "简介": "谋划诡计，激活头脑。大幅提高自己的特攻。", "属性": "恶", "类型": "变化", "威力": "—", "命中": "—", "PP": "20"}, "技能8": {"名称": "撒娇", "简介": "可爱地凝视，诱使对手疏忽大意，从而大幅降低对手的攻击。", "属性": "妖精", "类型": "变化", "威力": "—", "命中": "100", "PP": "20"}, "技能9": {"名称": "叫声", "简介": "让对手听可爱的叫声，引开注意力使其疏忽，从而降低对手的攻击。", "属性": "一般", "类型": "变化", "威力": "—", "命中": "100", "PP": "40"}, "技能10": {"名称": "电光一闪", "简介": "以迅雷不及掩耳之势扑向对手。必定能够先制攻击。", "属性": "一般", "类型": "物理", "威力": "40", "命中": "100", "PP": "30"}, "技能11": {"名称": "电磁波", "简介": "向对手发出微弱的电击，从而让对手陷入麻痹状态。", "属性": "电", "类型": "变化", "威力": "—", "命中": "90", "PP": "20"}, "技能12": {"名称": "影子分身", "简介": "通过快速移动来制造分身，扰乱对手，从而提高闪避率。", "属性": "一般", "类型": "变化", "威力": "—", "命中": "—", "PP": "15"}, "技能13": {"名称": "电球", "简介": "用电气团撞向对手。自己比对手速度越快，威力越大。", "属性": "电", "类型": "特殊", "威力": "变化", "命中": "100", "PP": "10"}, "技能14": {"名称": "佯攻", "简介": "能够攻击正在使用守住或看穿等招式的对手。解除其守护效果。", "属性": "一般", "类型": "物理", "威力": "30", "命中": "100", "PP": "10"}, "技能15": {"名称": "电光", "简介": "让电流覆盖全身，猛撞向对手进行攻击。有时会让对手陷入麻痹状态。", "属性": "电", "类型": "物理", "威力": "65", "命中": "100", "PP": "20"}, "技能16": {"名称": "高速移动", "简介": "让身体放松变得轻盈，以便高速移动。大幅提高自己的速度。", "属性": "超能", "类型": "变化", "威力": "—", "命中": "—", "PP": "30"}, "技能17": {"名称": "摔打", "简介": "使用长长的尾巴或藤蔓等摔打对手进行攻击。", "属性": "一般", "类型": "物理", "威力": "80", "命中": "75", "PP": "20"}, "技能18": {"名称": "放电", "简介": "用耀眼的电击攻击自己周围所有的宝可梦。有时会陷入麻痹状态。", "属性": "电", "类型": "特殊", "威力": "80", "命中": "100", "PP": "15"}, "技能19": {"名称": "十万伏特", "简介": "向对手发出强力电击进行攻击。有时会让对手陷入麻痹状态。", "属性": "电", "类型": "特殊", "威力": "90", "命中": "100", "PP": "15"}, "技能20": {"名称": "光墙", "简介": "在５回合内使用神奇的墙，减弱从对手那受到的特殊攻击的伤害。", "属性": "超能", "类型": "变化", "威力": "—", "命中": "—", "PP": "30"}, "技能21": {"名称": "打雷", "简介": "向对手劈下暴雷进行攻击。有时会让对手陷入麻痹状态。", "属性": "电", "类型": "特殊", "威力": "110", "命中": "70", "PP": "10"}, "技能22": {"名称": "百万吨重拳", "简介": "用充满力量的拳头攻击对手。", "属性": "一般", "类型": "物理", "威力": "80", "命中": "85", "PP": "20"}, "技能23": {"名称": "百万吨重踢", "简介": "使出力大无穷的重踢踢飞对手进行攻击。", "属性": "一般", "类型": "物理", "威力": "120", "命中": "75", "PP": "5"}, "技能24": {"名称": "聚宝功", "简介": "向对手的身体投掷小金币进行攻击。战斗后可以拿到钱。", "属性": "一般", "类型": "物理", "威力": "40", "命中": "100", "PP": "20"}, "技能25": {"名称": "破坏光线", "简介": "向对手发射强烈的光线进行攻击。下一回合自己将无法动弹。", "属性": "一般", "类型": "特殊", "威力": "150", "命中": "90", "PP": "5"}, "技能26": {"名称": "终极冲击", "简介": "使出自己浑身力量突击对手。下一回合自己将无法动弹。", "属性": "一般", "类型": "物理", "威力": "150", "命中": "90", "PP": "5"}, "技能27": {"名称": "挖洞", "简介": "第１回合钻入，第２回合攻击对手。", "属性": "地面", "类型": "物理", "威力": "80", "命中": "100", "PP": "10"}, "技能28": {"名称": "反射壁", "简介": "在５回合内使用神奇的墙，减弱从对手那受到的物理攻击的伤害。", "属性": "超能", "类型": "变化", "威力": "—", "命中": "—", "PP": "20"}, "技能29": {"名称": "神秘守护", "简介": "在５回合内被神奇的力量守护，从而不会陷入异常状态。", "属性": "一般", "类型": "变化", "威力": "—", "命中": "—", "PP": "25"}, "技能30": {"名称": "睡觉", "简介": "连续睡上２回合。回复自己的全部ＨＰ以及治愈所有异常状态。", "属性": "超能", "类型": "变化", "威力": "—", "命中": "—", "PP": "10"}, "技能31": {"名称": "小偷", "简介": "攻击的同时盗取道具。当自己携带道具时，不会去盗取。", "属性": "恶", "类型": "物理", "威力": "60", "命中": "100", "PP": "25"}, "技能32": {"名称": "打鼾", "简介": "在自己睡觉时，发出噪音进行攻击。有时会使对手畏缩。", "属性": "一般", "类型": "特殊", "威力": "50", "命中": "100", "PP": "15"}, "技能33": {"名称": "守住", "简介": "完全抵挡对手的攻击。连续使出则容易失败。", "属性": "一般", "类型": "变化", "威力": "—", "命中": "—", "PP": "10"}, "技能34": {"名称": "迷人", "简介": "♂诱惑♀或♀诱惑♂，让对手着迷。对手将很难使出招式。", "属性": "一般", "类型": "变化", "威力": "—", "命中": "100", "PP": "15"}, "技能35": {"名称": "求雨", "简介": "在５回合内一直降雨，从而提高水属性的招式威力。火属性的招式威力则降低。", "属性": "水", "类型": "变化", "威力": "—", "命中": "—", "PP": "5"}, "技能36": {"名称": "硬撑", "简介": "当自己处于中毒、麻痹、灼伤状态时，向对手使出此招式的话，威力会变成２倍。", "属性": "一般", "类型": "物理", "威力": "70", "命中": "100", "PP": "20"}, "技能37": {"名称": "高速星星", "简介": "发射星形的光攻击对手。攻击必定会命中。", "属性": "一般", "类型": "特殊", "威力": "60", "命中": "—", "PP": "20"}, "技能38": {"名称": "帮助", "简介": "帮助伙伴。被帮助的宝可梦，其招式威力变得比平时大。", "属性": "一般", "类型": "变化", "威力": "—", "命中": "—", "PP": "20"}, "技能39": {"名称": "劈瓦", "简介": "将手刀猛烈地挥下攻击对手。还可以破坏光墙和反射壁等。", "属性": "格斗", "类型": "物理", "威力": "75", "命中": "100", "PP": "15"}, "技能40": {"名称": "投掷", "简介": "快速投掷携带的道具进行攻击。根据道具不同，威力和效果会改变。", "属性": "恶", "类型": "物理", "威力": "—", "命中": "100", "PP": "10"}, "技能41": {"名称": "速度互换", "简介": "将对手和自己的速度进行互换。", "属性": "超能", "类型": "变化", "威力": "—", "命中": "—", "PP": "10"}, "技能42": {"名称": "轮唱", "简介": "用歌声攻击对手。同伴还可以接着使出轮唱招式，威力也会提高。", "属性": "一般", "类型": "特殊", "威力": "60", "命中": "100", "PP": "15"}, "技能43": {"名称": "伏特替换", "简介": "在攻击之后急速返回，和后备宝可梦进行替换。", "属性": "电", "类型": "特殊", "威力": "70", "命中": "100", "PP": "20"}, "技能44": {"名称": "电网", "简介": "用电网捉住对手进行攻击。降低对手的速度。", "属性": "电", "类型": "特殊", "威力": "55", "命中": "95", "PP": "15"}, "技能45": {"名称": "吸取之吻", "简介": "用一个吻吸取对手的ＨＰ。回复给予对手伤害的一半以上的ＨＰ。", "属性": "妖精", "类型": "特殊", "威力": "50", "命中": "100", "PP": "10"}, "技能46": {"名称": "电气场地", "简介": "在５回合内变成电气场地。地面上的宝可梦将无法入眠。电属性的招式威力还会提高。", "属性": "电", "类型": "变化", "威力": "—", "命中": "—", "PP": "10"}, "技能47": {"名称": "怪异电波", "简介": "从身体放射出怪异电波，让对手沐浴其中，从而大幅降低其特攻。", "属性": "电", "类型": "变化", "威力": "—", "命中": "100", "PP": "15"}, "技能48": {"名称": "狂舞挥打", "简介": "用自己的身体狂舞挥打，给予对手伤害。", "属性": "恶", "类型": "物理", "威力": "60", "命中": "100", "PP": "20"}, "技能49": {"名称": "泰山压顶", "简介": "用整个身体压住对手进行攻击。有时会让对手陷入麻痹状态。", "属性": "一般", "类型": "物理", "威力": "85", "命中": "100", "PP": "15"}, "技能50": {"名称": "冲浪", "简介": "利用大浪攻击自己周围所有的宝可梦。", "属性": "水", "类型": "特殊", "威力": "90", "命中": "100", "PP": "15"}, "技能51": {"名称": "替身", "简介": "削减少许自己的ＨＰ，制造分身。分身将成为自己的替身。", "属性": "一般", "类型": "变化", "威力": "—", "命中": "—", "PP": "10"}, "技能52": {"名称": "起死回生", "简介": "竭尽全力进行攻击。自己的ＨＰ越少，招式的威力越大。", "属性": "格斗", "类型": "物理", "威力": "—", "命中": "100", "PP": "15"}, "技能53": {"名称": "挺住", "简介": "即使受到攻击，也至少会留下１ＨＰ。连续使出则容易失败。", "属性": "一般", "类型": "变化", "威力": "—", "命中": "—", "PP": "10"}, "技能54": {"名称": "梦话", "简介": "从自己已学会的招式中任意使出１个。只能在自己睡觉时使用。", "属性": "一般", "类型": "变化", "威力": "—", "命中": "—", "PP": "10"}, "技能55": {"名称": "再来一次", "简介": "让对手接受再来一次，连续３次使出最后使用的招式。", "属性": "一般", "类型": "变化", "威力": "—", "命中": "100", "PP": "5"}, "技能56": {"名称": "铁尾", "简介": "使用坚硬的尾巴摔打对手进行攻击。有时会降低对手的防御。", "属性": "钢", "类型": "物理", "威力": "100", "命中": "75", "PP": "15"}, "技能57": {"名称": "吵闹", "简介": "在３回合内用骚乱攻击对手。在此期间谁都不能入眠。", "属性": "一般", "类型": "特殊", "威力": "90", "命中": "100", "PP": "10"}, "技能58": {"名称": "真气弹", "简介": "提高气势，释放出全部力量。有时会降低对手的特防。", "属性": "格斗", "类型": "特殊", "威力": "120", "命中": "70", "PP": "5"}, "技能59": {"名称": "打草结", "简介": "用草缠住并绊倒对手。对手越重，威力越大。", "属性": "草", "类型": "特殊", "威力": "—", "命中": "100", "PP": "20"}, "技能60": {"名称": "电球", "简介": "用电气团撞向对手。自己比对手速度越快，威力越大。", "属性": "电", "类型": "特殊", "威力": "—", "命中": "100", "PP": "10"}, "技能61": {"名称": "疯狂伏特", "简介": "让电流覆盖全身撞向对手进行攻击。自己也会受到少许伤害。", "属性": "电", "类型": "物理", "威力": "90", "命中": "100", "PP": "15"}, "技能62": {"名称": "嬉闹", "简介": "与对手嬉闹并攻击。有时会降低对手的攻击。", "属性": "妖精", "类型": "物理", "威力": "90", "命中": "90", "PP": "10"}, "技能63": {"名称": "充电", "简介": "提高下一回合使出的电属性的招式威力。自己的特防也会提高。", "属性": "电", "类型": "变化", "威力": "—", "命中": "—", "PP": "20"}, "技能64": {"名称": "魅惑之声", "简介": "发出魅惑的叫声，给予对手精神上的伤害。攻击必定会命中。", "属性": "妖精", "类型": "特殊", "威力": "40", "命中": "—", "PP": "15"}, "技能65": {"名称": "击掌奇袭", "简介": "进行先制攻击，使对手畏缩。要在出场后立刻使出才能成功。", "属性": "一般", "类型": "物理", "威力": "40", "命中": "100", "PP": "10"}, "技能66": {"名称": "抓狂", "简介": "抓狂般乱打进行攻击。自己的ＨＰ越少，招式的威力越大。", "属性": "一般", "类型": "物理", "威力": "—", "命中": "100", "PP": "15"}, "技能67": {"名称": "礼物", "简介": "递给对手设有圈套的盒子进行攻击。也有可能回复对手ＨＰ。", "属性": "一般", "类型": "物理", "威力": "—", "命中": "90", "PP": "15"}, "技能68": {"名称": "祈愿", "简介": "在下一回合回复自己或是替换出场的宝可梦最大ＨＰ的一半。", "属性": "一般", "类型": "变化", "威力": "—", "命中": "—", "PP": "10"}, "技能69": {"名称": "挠痒", "简介": "给对手挠痒，使其发笑，从而降低对手的攻击和防御。", "属性": "一般", "类型": "变化", "威力": "—", "命中": "100", "PP": "20"}, "技能70": {"名称": "伏特攻击", "简介": "如果其一亲代拥有电气球，皮丘就会学会伏特攻击，伏特攻击不能通过培育学会。", "属性": "电", "类型": "物理", "威力": "120", "命中": "100", "PP": "15"}}